everyrow_mcp/__init__.py
everyrow_mcp/server.py
everyrow_mcp/utils.py
everyrow_mcp-0.1.10.dist-info/METADATA
everyrow_mcp-0.1.10.dist-info/WHEEL
everyrow_mcp-0.1.10.dist-info/entry_points.txt
everyrow_mcp-0.1.10.dist-info/RECORD
