Metadata-Version: 2.4
Name: everyrow-mcp
Version: 0.1.10
Summary: MCP server for everyrow: agent ops at spreadsheet scale
Requires-Python: >=3.12
Requires-Dist: everyrow>=0.1.5
Requires-Dist: mcp[cli]>=1.0.0
Requires-Dist: pandas>=2.0.0
Requires-Dist: pydantic<3.0.0,>=2.0.0
